fastapi_enum_errors/__init__.py
fastapi_enum_errors/error_enum.py
fastapi_enum_errors/exception.py
fastapi_enum_errors/extended_enum.py
fastapi_enum_errors/handler.py
fastapi_enum_errors/models.py
fastapi_enum_errors/py.typed
fastapi_enum_errors-0.2.2.dist-info/METADATA
fastapi_enum_errors-0.2.2.dist-info/WHEEL
fastapi_enum_errors-0.2.2.dist-info/licenses/LICENSE
fastapi_enum_errors-0.2.2.dist-info/RECORD
