Metadata-Version: 2.4
Name: fastapi_enum_errors
Version: 0.2.2
Summary: Addon for FastAPI that simplifies working with custom errors and allows you to operate on them as if they were values in an Enum.
License-Expression: MIT
License-File: LICENSE
Requires-Python: >=3.12
Requires-Dist: fastapi>=0.115.12
Requires-Dist: httpx>=0.28.1
Requires-Dist: pydantic>=2.11.0
